<?xml version='1.0' encoding='utf-8'?>
<data>
	<interval id="0" begin="0" end="3600">
		<edge id="1220032803" entered="259" />
		<edge id="1220030002" entered="248" />
		<edge id="1220032903" entered="247" />
		<edge id="1220030102" entered="312" />
		<edge id="1220025002" entered="436" />
		<edge id="1220025103" entered="440" />
		<edge id="1220014302" entered="350" />
		<edge id="1220014201" entered="382" />
		<edge id="1220026302" entered="286" />
		<edge id="1220026202" entered="302" />
		<edge id="1220023902" entered="166" />
		<edge id="1220023801" entered="192" />
		<edge id="1220026103" entered="390" />
		<edge id="1220026003" entered="420" />
		<edge id="1220027402" entered="405" />
		<edge id="1220027502" entered="477" />
		<edge id="1220027702" entered="160" />
		<edge id="1220027602" entered="171" />
		<edge id="1220036102" entered="322" />
		<edge id="1220036003" entered="270" />
		<edge id="1220029302" entered="269" />
		<edge id="1220029201" entered="273" />
		<edge id="1220034602" entered="405" />
		<edge id="1220034702" entered="469" />
		<edge id="1220003403" entered="611" />
		<edge id="1220003302" entered="549" />
		<edge id="1220020902" entered="377" />
		<edge id="1220020802" entered="370" />
	</interval>
	<interval id="1" begin="3600" end="7200">
		<edge id="1220032803" entered="309" />
		<edge id="1220030002" entered="263" />
		<edge id="1220032903" entered="294" />
		<edge id="1220030102" entered="335" />
		<edge id="1220025002" entered="473" />
		<edge id="1220025103" entered="433" />
		<edge id="1220014302" entered="387" />
		<edge id="1220014201" entered="396" />
		<edge id="1220026302" entered="318" />
		<edge id="1220026202" entered="312" />
		<edge id="1220023902" entered="179" />
		<edge id="1220023801" entered="218" />
		<edge id="1220026103" entered="392" />
		<edge id="1220026003" entered="442" />
		<edge id="1220027402" entered="426" />
		<edge id="1220027502" entered="537" />
		<edge id="1220027702" entered="195" />
		<edge id="1220027602" entered="205" />
		<edge id="1220036102" entered="303" />
		<edge id="1220036003" entered="296" />
		<edge id="1220029302" entered="302" />
		<edge id="1220029201" entered="306" />
		<edge id="1220034602" entered="412" />
		<edge id="1220034702" entered="495" />
		<edge id="1220003403" entered="596" />
		<edge id="1220003302" entered="559" />
		<edge id="1220020902" entered="401" />
		<edge id="1220020802" entered="354" />
	</interval>
	<interval id="2" begin="7200" end="10800">
		<edge id="1220032803" entered="348" />
		<edge id="1220030002" entered="299" />
		<edge id="1220032903" entered="354" />
		<edge id="1220030102" entered="374" />
		<edge id="1220025002" entered="553" />
		<edge id="1220025103" entered="499" />
		<edge id="1220014302" entered="426" />
		<edge id="1220014201" entered="450" />
		<edge id="1220026302" entered="322" />
		<edge id="1220026202" entered="342" />
		<edge id="1220023902" entered="205" />
		<edge id="1220023801" entered="234" />
		<edge id="1220026103" entered="413" />
		<edge id="1220026003" entered="437" />
		<edge id="1220027402" entered="438" />
		<edge id="1220027502" entered="576" />
		<edge id="1220027702" entered="206" />
		<edge id="1220027602" entered="210" />
		<edge id="1220036102" entered="324" />
		<edge id="1220036003" entered="332" />
		<edge id="1220029302" entered="321" />
		<edge id="1220029201" entered="335" />
		<edge id="1220034602" entered="491" />
		<edge id="1220034702" entered="509" />
		<edge id="1220003403" entered="612" />
		<edge id="1220003302" entered="557" />
		<edge id="1220020902" entered="458" />
		<edge id="1220020802" entered="395" />
	</interval>
	<interval id="3" begin="10800" end="14400">
		<edge id="1220032803" entered="302" />
		<edge id="1220030002" entered="304" />
		<edge id="1220032903" entered="329" />
		<edge id="1220030102" entered="370" />
		<edge id="1220025002" entered="565" />
		<edge id="1220025103" entered="530" />
		<edge id="1220014302" entered="439" />
		<edge id="1220014201" entered="415" />
		<edge id="1220026302" entered="311" />
		<edge id="1220026202" entered="300" />
		<edge id="1220023902" entered="205" />
		<edge id="1220023801" entered="227" />
		<edge id="1220026103" entered="378" />
		<edge id="1220026003" entered="425" />
		<edge id="1220027402" entered="364" />
		<edge id="1220027502" entered="563" />
		<edge id="1220027702" entered="206" />
		<edge id="1220027602" entered="163" />
		<edge id="1220036102" entered="320" />
		<edge id="1220036003" entered="288" />
		<edge id="1220029302" entered="313" />
		<edge id="1220029201" entered="331" />
		<edge id="1220034602" entered="474" />
		<edge id="1220034702" entered="484" />
		<edge id="1220003403" entered="508" />
		<edge id="1220003302" entered="532" />
		<edge id="1220020902" entered="436" />
		<edge id="1220020802" entered="395" />
	</interval>
	<interval id="4" begin="14400" end="18000">
		<edge id="1220032803" entered="234" />
		<edge id="1220030002" entered="228" />
		<edge id="1220032903" entered="321" />
		<edge id="1220030102" entered="332" />
		<edge id="1220025002" entered="442" />
		<edge id="1220025103" entered="405" />
		<edge id="1220014302" entered="366" />
		<edge id="1220014201" entered="316" />
		<edge id="1220026302" entered="285" />
		<edge id="1220026202" entered="304" />
		<edge id="1220023902" entered="158" />
		<edge id="1220023801" entered="185" />
		<edge id="1220026103" entered="324" />
		<edge id="1220026003" entered="348" />
		<edge id="1220027402" entered="321" />
		<edge id="1220027502" entered="473" />
		<edge id="1220027702" entered="181" />
		<edge id="1220027602" entered="173" />
		<edge id="1220036102" entered="303" />
		<edge id="1220036003" entered="266" />
		<edge id="1220029302" entered="241" />
		<edge id="1220029201" entered="314" />
		<edge id="1220034602" entered="323" />
		<edge id="1220034702" entered="381" />
		<edge id="1220003403" entered="497" />
		<edge id="1220003302" entered="509" />
		<edge id="1220020902" entered="348" />
		<edge id="1220020802" entered="335" />
	</interval>
	<interval id="5" begin="18000" end="21600">
		<edge id="1220032803" entered="181" />
		<edge id="1220030002" entered="199" />
		<edge id="1220032903" entered="234" />
		<edge id="1220030102" entered="257" />
		<edge id="1220025002" entered="367" />
		<edge id="1220025103" entered="318" />
		<edge id="1220014302" entered="313" />
		<edge id="1220014201" entered="232" />
		<edge id="1220026302" entered="258" />
		<edge id="1220026202" entered="273" />
		<edge id="1220023902" entered="120" />
		<edge id="1220023801" entered="141" />
		<edge id="1220026103" entered="290" />
		<edge id="1220026003" entered="258" />
		<edge id="1220027402" entered="324" />
		<edge id="1220027502" entered="414" />
		<edge id="1220027702" entered="136" />
		<edge id="1220027602" entered="146" />
		<edge id="1220036102" entered="242" />
		<edge id="1220036003" entered="213" />
		<edge id="1220029302" entered="189" />
		<edge id="1220029201" entered="195" />
		<edge id="1220034602" entered="216" />
		<edge id="1220034702" entered="289" />
		<edge id="1220003403" entered="413" />
		<edge id="1220003302" entered="385" />
		<edge id="1220020902" entered="306" />
		<edge id="1220020802" entered="255" />
	</interval>
	<interval id="6" begin="21600" end="25200">
		<edge id="1220032803" entered="171" />
		<edge id="1220030002" entered="182" />
		<edge id="1220032903" entered="224" />
		<edge id="1220030102" entered="254" />
		<edge id="1220025002" entered="305" />
		<edge id="1220025103" entered="292" />
		<edge id="1220014302" entered="297" />
		<edge id="1220014201" entered="249" />
		<edge id="1220026302" entered="257" />
		<edge id="1220026202" entered="259" />
		<edge id="1220023902" entered="130" />
		<edge id="1220023801" entered="152" />
		<edge id="1220026103" entered="265" />
		<edge id="1220026003" entered="253" />
		<edge id="1220027402" entered="324" />
		<edge id="1220027502" entered="353" />
		<edge id="1220027702" entered="111" />
		<edge id="1220027602" entered="134" />
		<edge id="1220036102" entered="213" />
		<edge id="1220036003" entered="234" />
		<edge id="1220029302" entered="173" />
		<edge id="1220029201" entered="201" />
		<edge id="1220034602" entered="207" />
		<edge id="1220034702" entered="275" />
		<edge id="1220003403" entered="379" />
		<edge id="1220003302" entered="357" />
		<edge id="1220020902" entered="233" />
		<edge id="1220020802" entered="183" />
	</interval>
</data>